.gitignore
LICENSE
README.md
initial.svg
pyproject.toml
docs/add-enhancement.md
docs/add-legend.md
docs/complete-occlusion-adaptation.md
docs/create-representations.md
docs/experiment-help-interface.md
docs/experiment-simultaneous-representations.md
docs/export-hand-poses.md
docs/inkscape-installation-steps.md
docs/map-commands.md
docs/images/microRep.png
docs/images/microRep.svg
docs/images/microRep_full.png
docs/images/microRep_horizontal.png
docs/images/microRep_vertical.png
docs/images/python_logo.png
src/microrep/__init__.py
src/microrep/add_enhancement.inx
src/microrep/add_legend.inx
src/microrep/add_overlap_adaptation.inx
src/microrep/create_representations.inx
src/microrep/export_hand_poses.inx
src/microrep/map_commands.inx
src/microrep.egg-info/PKG-INFO
src/microrep.egg-info/SOURCES.txt
src/microrep.egg-info/dependency_links.txt
src/microrep.egg-info/requires.txt
src/microrep.egg-info/top_level.txt
src/microrep/add_enhancement/__init__.py
src/microrep/add_enhancement/add_enhancement.py
src/microrep/add_enhancement/configuration_file.py
src/microrep/add_legend/__init__.py
src/microrep/add_legend/add_legend.py
src/microrep/add_legend/configuration_file.py
src/microrep/add_legend/legends/LegendFive.svg
src/microrep/add_legend/legends/LegendFour.svg
src/microrep/add_legend/legends/LegendOne.svg
src/microrep/add_legend/legends/LegendSix.svg
src/microrep/add_legend/legends/LegendThree.svg
src/microrep/add_legend/legends/LegendTwo.svg
src/microrep/add_overlap_adaptation/__init__.py
src/microrep/add_overlap_adaptation/add_overlap_adaptation.py
src/microrep/add_overlap_adaptation/configuration_file.py
src/microrep/core/README.md
src/microrep/core/__init__.py
src/microrep/core/export.py
src/microrep/core/mg_maths.py
src/microrep/core/ref_and_specs.py
src/microrep/core/scale_mg_rep.py
src/microrep/core/utils.py
src/microrep/create_representations/__init__.py
src/microrep/create_representations/configuration_file.py
src/microrep/create_representations/create_mg_rep.py
src/microrep/create_representations/create_representations.py
src/microrep/export_hand_poses/__init__.py
src/microrep/export_hand_poses/configuration_file.py
