Metadata-Version: 2.4
Name: microrep
Version: 1.0.0
Summary: An Inkscape extension with allows to create and modify hand postures and representations of hand microgestures with or without the associated commands. This work has been initiated for the experiences presented in the paper 'Studying the Simultaneous Representations of Microgestures' published by MobileHCI 2024.
Author-email: Vincent Lambert <vincent.lambert29@gmail.com>
Project-URL: Homepage, https://github.com/Vincent-LAMBERT/inkscape-microgestures
Project-URL: Issues, https://github.com/Vincent-LAMBERT/inkscape-microgestures/issues
Keywords: microgesture,representation,illustration,hand,fingers,gesture
Classifier: Programming Language :: Python :: 3
Classifier: License :: OSI Approved :: MIT License
Classifier: Operating System :: OS Independent
Requires-Python: >=3.8
License-File: LICENSE
Requires-Dist: requests
Requires-Dist: importlib-metadata; python_version < "3.8"
Requires-Dist: inkex>=1.4.1
Requires-Dist: lxml>=5.4.0
Requires-Dist: Shapely>=2.1.1
Requires-Dist: svg.path>=6.3
Provides-Extra: test
Requires-Dist: cairosvg; extra == "test"
Dynamic: license-file
